videoslicer/__init__.py
videoslicer/crs.py
videoslicer/markers.py
videoslicer/utils.py
videoslicer/videoslicer.py
videoslicer-1.0.0rc2.dist-info/DESCRIPTION.rst
videoslicer-1.0.0rc2.dist-info/METADATA
videoslicer-1.0.0rc2.dist-info/RECORD
videoslicer-1.0.0rc2.dist-info/WHEEL
videoslicer-1.0.0rc2.dist-info/metadata.json
videoslicer-1.0.0rc2.dist-info/top_level.txt
